sphere_can/__init__.py
sphere_can/config.py
sphere_can/main.py
sphere_can/readcan.py
sphere_can/sendcan.py
sphere_can/setup.py
sphere_can/status.py
sphere_can/stop.py
sphere_can-0.1.4.dist-info/METADATA
sphere_can-0.1.4.dist-info/WHEEL
sphere_can-0.1.4.dist-info/entry_points.txt
sphere_can-0.1.4.dist-info/top_level.txt
sphere_can-0.1.4.dist-info/RECORD
