Metadata-Version: 2.4
Name: sphere-can
Version: 0.1.4
Summary: SPHERE CAN command-line interface
License: MIT
Requires-Python: >=3.9
Requires-Dist: typer
Requires-Dist: requests
Requires-Dist: websocket-client
